[{"id":"654208f1f5682e8b1277b056","title":"旗袍姐","author":"文／李座峰","editor":"（责任编辑：贺伊曼） "},{"id":"654208f3f5682e8b1277b058","title":"老菊的歌","author":"文／熊德启","editor":"（责任编辑：一言） "},{"id":"654208f6f5682e8b1277b05a","title":"樱花与森林","author":"文／曹畅洲","editor":"责任编辑：金子棋 jinziqi@wufazhuce.com"},{"id":"654208f8f5682e8b1277b05c","title":"把所有套套都带上","author":"文／大头马","editor":"（责任编辑：金子棋） "},{"id":"654208faf5682e8b1277b05e","title":"姐姐","author":"文／耀一","editor":"（责任编辑：金子棋） "},{"id":"654208fcf5682e8b1277b060","title":"白糖饼往事","author":"文／吴虹飞","editor":"（责任编辑：金子棋） "},{"id":"654208fff5682e8b1277b062","title":"无从告别的告别","author":"文／里则林","editor":"（责任编辑：金子棋） "},{"id":"65420901f5682e8b1277b064","title":"三个好朋友","author":"文／夜X","editor":"（责任编辑：金子棋） "},{"id":"65420903f5682e8b1277b066","title":"因为胖过","author":"文／咸贵人","editor":"（责任编辑：薛诗汉） "},{"id":"65420905f5682e8b1277b068","title":"睡不着","author":"文／路明","editor":"责任编辑：薛诗汉 onewenzhang@wufazhuce.com"},{"id":"65420908f5682e8b1277b06a","title":"悲伤的冰淇淋曲","author":"文／黄可","editor":"（责任编辑：贺伊曼） "},{"id":"6542090af5682e8b1277b06c","title":"追我女朋友的那家伙！","author":"文／王若虚","editor":"（责任编辑：向可） "},{"id":"6542090cf5682e8b1277b06e","title":"胖子海力布","author":"文／李座峰","editor":"（责任编辑：贺伊曼） "},{"id":"6542090ef5682e8b1277b070","title":"硬糖","author":"文／姚瑶","editor":"（责任编辑：贺伊曼） "},{"id":"65420911f5682e8b1277b072","title":"红裙","author":"文／刘文","editor":"（责任编辑：向可） "},{"id":"65420913f5682e8b1277b074","title":"杯酒过往","author":"文／王路","editor":"（责任编辑：薛诗汉） "},{"id":"65420915f5682e8b1277b076","title":"特别不浪漫","author":"文／刘墨闻","editor":"（责任编辑：金子棋） "},{"id":"65420917f5682e8b1277b078","title":"不只是爱情故事而已","author":"文／F小姐","editor":"（责任编辑：向可） "},{"id":"6542091af5682e8b1277b07a","title":"姐姐，今夜我在西什库","author":"文／阿梵","editor":"（责任编辑：一言） "},{"id":"6542091cf5682e8b1277b07c","title":"你不用回来","author":"文／烟波人长安","editor":"（责任编辑：赵西栋） "},{"id":"6542091ef5682e8b1277b07e","title":"我不在你身边的第五百年","author":"文／李遥策","editor":"（责任编辑：金子棋） "},{"id":"65420920f5682e8b1277b080","title":"借书的人死掉了","author":"文／沈大成","editor":"（责任编辑：金子棋） "},{"id":"65420923f5682e8b1277b082","title":"再无晴朗天气，就自己成为风景","author":"文／张皓宸","editor":"（责任编辑：一言） "},{"id":"65420925f5682e8b1277b084","title":"快递盒子的秘密","author":"文／曲玮玮","editor":"（责任编辑：一言） "},{"id":"65420927f5682e8b1277b086","title":"头等舱","author":"文／顾颖","editor":"（责任编辑：向可） "},{"id":"65420929f5682e8b1277b088","title":"不吃肉的小孩","author":"文／倪一宁","editor":"（责任编辑：一言） "},{"id":"6542092cf5682e8b1277b08a","title":"一个歌手的情书","author":"文／大冰","editor":"（责任编辑：赵西栋） "},{"id":"65420934f5682e8b1277b08c","title":"世界和你说了声Hi","author":"文／张晓晗","editor":"（责任编辑：一言） "},{"id":"65420937f5682e8b1277b08e","title":"钟馗的剑","author":"文／陈坤","editor":"（责任编辑：赵西栋） "},{"id":"65420939f5682e8b1277b090","title":"过年机器人","author":"文／荞麦","editor":"责任编辑：金子棋 jinziqi@wufazhuce.com"},{"id":"6542093bf5682e8b1277b092","title":"独臂刀","author":"文／戴正阳","editor":"（责任编辑：薛诗汉） "},{"id":"6542093df5682e8b1277b094","title":"她们","author":"文／鲸书","editor":"（责任编辑：薛诗汉） "},{"id":"65420940f5682e8b1277b096","title":"兰州莎莎","author":"文／赵纯想","editor":"（责任编辑：一言） "},{"id":"65420942f5682e8b1277b098","title":"林太与安生","author":"文／午歌","editor":"（责任编辑：郭佳杰） "},{"id":"65420945f5682e8b1277b09a","title":"枕边书","author":"文／阿白","editor":"（责任编辑：郭佳杰） "},{"id":"65420947f5682e8b1277b09c","title":"你离开了南京","author":"文／破罐","editor":"责任编辑：郭佳杰 onewenzhang@wufazhuce.com"},{"id":"65420949f5682e8b1277b09e","title":"醉酒","author":"文／路明","editor":"（责任编辑：薛诗汉） "},{"id":"6542094bf5682e8b1277b0a0","title":"看脸","author":"文／魏天一","editor":"（责任编辑：金子棋） "},{"id":"6542094ef5682e8b1277b0a2","title":"朋友们，能不能先把手机放一旁","author":"文／慢三","editor":"（责任编辑：薛诗汉） "},{"id":"65420950f5682e8b1277b0a4","title":"七十一先生","author":"文／于夕","editor":"（责任编辑：薛诗汉） "},{"id":"65420952f5682e8b1277b0a6","title":"失乐人 ","author":"文／方慧","editor":"（责任编辑：赵西栋） "},{"id":"65420955f5682e8b1277b0a8","title":"一个标准的童话故事","author":"文／颜茹玉","editor":"（责任编辑：贺伊曼） "},{"id":"65420957f5682e8b1277b0aa","title":"一个人的北京","author":"文／咸贵人","editor":"责任编辑：薛诗汉 onewenzhang@wufazhuce.com"},{"id":"6542095af5682e8b1277b0ac","title":"爸爸的背影","author":"文／马徐骏","editor":"（责任编辑：郭佳杰） "},{"id":"6542095cf5682e8b1277b0ae","title":"我们说了沉默就沉默到底","author":"文／李诞","editor":"（责任编辑：薛诗汉） "},{"id":"6542095ef5682e8b1277b0b0","title":"北方有盛宴","author":"文／吴惠子","editor":"（责任编辑：一言） "},{"id":"65420960f5682e8b1277b0b2","title":"猫语症","author":"文／张寒寺","editor":"责任编辑：薛诗汉 onewenzhang@wufazhuce.com"},{"id":"65420962f5682e8b1277b0b4","title":"几个再见","author":"文／沈大成","editor":"（责任编辑：金子棋） "},{"id":"65420965f5682e8b1277b0b6","title":"逆流者","author":"文／阿缺","editor":"（责任编辑：金子棋） "},{"id":"65420967f5682e8b1277b0b8","title":"和酒说话的人","author":"文／春晓","editor":"（责任编辑：赵西栋） "},{"id":"65420969f5682e8b1277b0ba","title":"一次别离","author":"文／毛利","editor":"（责任编辑：薛诗汉） "},{"id":"6542096cf5682e8b1277b0bc","title":"活着便是平淡一生最好的安慰","author":"文／张皓宸","editor":"（责任编辑：一言） "},{"id":"6542096ff5682e8b1277b0be","title":"圣诞故事","author":"文／崔罗石","editor":"责任编辑：贺伊曼 onewenzhang@wufazhuce.com"},{"id":"65420971f5682e8b1277b0c0","title":"倒塌的积木","author":"文／顾颖","editor":"（责任编辑：向可） "},{"id":"65420973f5682e8b1277b0c2","title":"白果","author":"文／苏更生","editor":"（见习编辑：郭佳杰） "},{"id":"65420975f5682e8b1277b0c4","title":"颗粒的秘密","author":"文／魏天一","editor":"（责任编辑：金子棋） "},{"id":"65420978f5682e8b1277b0c6","title":"这原本应该是个悲伤的故事","author":"文／尸姐","editor":"（责任编辑：赵西栋） "},{"id":"6542097af5682e8b1277b0c8","title":"腿","author":"文／周耀辉","editor":"（责任编辑：薛诗汉） "},{"id":"6542097cf5682e8b1277b0ca","title":"听《Reality》的女人","author":"文／赵纯想","editor":"（责任编辑：一言） "},{"id":"6542097ef5682e8b1277b0cc","title":"拉萨动物园","author":"文／沈祎","editor":"（责任编辑：贺伊曼） "},{"id":"65420981f5682e8b1277b0ce","title":"旅程","author":"文／刘文","editor":"（责任编辑：向可） "},{"id":"65420983f5682e8b1277b0d0","title":"我就在这，哪也不去","author":"文／赵聪","editor":"（见习编辑：郭佳杰） "},{"id":"65420985f5682e8b1277b0d2","title":"我们会好吗，还是会更糟","author":"文／蒋话","editor":"（责任编辑：金子棋）  "},{"id":"65420987f5682e8b1277b0d4","title":"人类动物园","author":"文／林西拿","editor":"（责任编辑：赵西栋） "},{"id":"6542098af5682e8b1277b0d6","title":"感恩的心","author":"文／陈麒凌","editor":"（责任编辑：薛诗汉） "},{"id":"6542098cf5682e8b1277b0d8","title":"如果你不曾撩动我的心弦","author":"文／吴惠子","editor":"（责任编辑：一言） "},{"id":"6542098ef5682e8b1277b0da","title":"小狗饼干","author":"文／哥舒意","editor":"责任编辑：贺伊曼 onewenzhang@wufazhuce.com"},{"id":"65420990f5682e8b1277b0dc","title":"地铁里的武士","author":"文／王若虚","editor":"（责任编辑：向可） "},{"id":"65420993f5682e8b1277b0de","title":"影子外婆","author":"文／天空路","editor":"见习编辑：郭佳杰 onewenzhang@wufazhuce.com"},{"id":"65420995f5682e8b1277b0e0","title":"深埋心底的名字","author":"文／马叛","editor":"（责任编辑：金子棋） "},{"id":"65420997f5682e8b1277b0e2","title":"无名童话","author":"文／叫兽易小星","editor":"（责任编辑：赵西栋） "},{"id":"65420999f5682e8b1277b0e4","title":"更好的世界","author":"文／痞人日记","editor":"（责任编辑：薛诗汉） "},{"id":"6542099cf5682e8b1277b0e6","title":"孤单合租房","author":"文／朱肖影","editor":"责任编辑：一言 onewenzhang@wufazhuce.com"},{"id":"6542099ef5682e8b1277b0e8","title":"我知女人心","author":"文／李驰翔","editor":"（责任编辑：贺伊曼） "},{"id":"654209a0f5682e8b1277b0ea","title":"南方饺子馆","author":"文／扬卡洛夫","editor":"（责任编辑：向可） "},{"id":"654209a2f5682e8b1277b0ec","title":"天才文展","author":"文／蔡崇达","editor":"（见习编辑：郭佳杰） "},{"id":"654209a5f5682e8b1277b0ee","title":"不信人间有白头","author":"文／刘音希","editor":"（责任编辑：金子棋） "},{"id":"654209a7f5682e8b1277b0f0","title":"唱歌的人不许掉眼泪","author":"文／大冰","editor":"（责任编辑：赵西栋） "},{"id":"654209a9f5682e8b1277b0f2","title":"听房","author":"文／李诞","editor":"责任编辑：薛诗汉 onewenzhang@wufazhuce.com"},{"id":"654209abf5682e8b1277b0f4","title":"扮鳄鱼的人","author":"文／姬霄","editor":"（责任编辑：一言） "},{"id":"654209aef5682e8b1277b0f6","title":"伦敦的呼唤","author":"文／易小荷","editor":"责任编辑：贺伊曼 onewenzhang@wufazhuce.com"},{"id":"654209b0f5682e8b1277b0f8","title":"杀信鸽的人","author":"文／郑执","editor":"（责任编辑：向可） "},{"id":"654209b2f5682e8b1277b0fa","title":"废物","author":"文／慕容素衣","editor":"（见习编辑：郭佳杰） "},{"id":"654209b4f5682e8b1277b0fc","title":"清醒的梦","author":"文／蒋话","editor":"（责任编辑：金子棋） "},{"id":"654209b7f5682e8b1277b0fe","title":"异乡客和老克勒","author":"文／陈小熊","editor":"（责任编辑：赵西栋） "},{"id":"654209b9f5682e8b1277b100","title":"金沙湾水族","author":"文／慢三","editor":"（责任编辑：薛诗汉） "},{"id":"654209bbf5682e8b1277b102","title":"随手转发正能量","author":"文／张皓宸","editor":"（责任编辑：一言） "},{"id":"654209bdf5682e8b1277b104","title":"钻石有限公司","author":"文／张晓晗","editor":"（责任编辑：贺伊曼） "},{"id":"654209c0f5682e8b1277b106","title":"无根植物","author":"文／红肚兜儿","editor":"（责任编辑：向可） "},{"id":"654209c2f5682e8b1277b108","title":"西建大革命事件始末","author":"文／老K","editor":"（见习编辑：郭佳杰） "},{"id":"654209c4f5682e8b1277b10a","title":"更好的","author":"文／睡时猫","editor":"（责任编辑：金子棋） "},{"id":"654209c6f5682e8b1277b10c","title":"将次先生的冬信","author":"文／耀一","editor":"（责任编辑：赵西栋） "},{"id":"654209c9f5682e8b1277b10e","title":"老男人","author":"文／路明","editor":"（责任编辑：薛诗汉） "},{"id":"654209cbf5682e8b1277b110","title":"飘雪的芭蕾","author":"文／刘东明","editor":"（责任编辑：一言） "},{"id":"654209cdf5682e8b1277b112","title":"眼前的苟且，也正是诗和远方","author":"文／李松蔚","editor":"（责任编辑：贺伊曼） "},{"id":"654209cff5682e8b1277b114","title":"听见","author":"文／红俗手","editor":"（责任编辑：向可） "},{"id":"654209d2f5682e8b1277b116","title":"睡","author":"文／唐浚","editor":"见习编辑：郭佳杰 onewenzhang@wufazhuce.com"},{"id":"654209d4f5682e8b1277b118","title":"触不到的恋人","author":"文／刘墨闻","editor":"（责任编辑：金子棋） "},{"id":"654209d6f5682e8b1277b11a","title":"死神的管理培训生","author":"文／陈谌","editor":"（责任编辑：赵西栋） "},{"id":"654209d8f5682e8b1277b11c","title":"伤痕","author":"文／咸贵人","editor":"（责任编辑：薛诗汉） "}]