[{"id":"6542110bf5682e8b1277b75e","title":"撒谎判重罪","author":"文／陈伟","editor":"（责任编辑：卫天成） "},{"id":"6542110ef5682e8b1277b760","title":"你今天真好看","author":"文／那多","editor":"（责任编辑：卫天成） "},{"id":"65421110f5682e8b1277b762","title":"小孩的世界里没有小事","author":"文／王悦微","editor":"责任编辑：卫天成 weitiancheng@wufazhuce.com"},{"id":"65421112f5682e8b1277b764","title":"那个谁","author":"文／马一木","editor":"（责任编辑：卫天成） "},{"id":"65421114f5682e8b1277b766","title":"人间卧底","author":"文／马良","editor":"（责任编辑：卫天成） "},{"id":"65421117f5682e8b1277b768","title":"马未都先生，你以为那就是纯洁","author":"文／押沙龙","editor":"（责任编辑：卫天成） "},{"id":"65421119f5682e8b1277b76a","title":"失踪的暗物质","author":"文／走走","editor":"（责任编辑：卫天成） "},{"id":"6542111bf5682e8b1277b76c","title":"两枚戒指","author":"文／毛利","editor":"（责任编辑：卫天成） "},{"id":"6542111df5682e8b1277b76e","title":"有钱","author":"文／小饭","editor":"（见习编辑：黄点点） "},{"id":"6542111ff5682e8b1277b770","title":"躲避诗","author":"文／蔡康永","editor":"（责任编辑：薛诗汉） "},{"id":"65421122f5682e8b1277b772","title":"花街往事·疯人之家","author":"文／路内","editor":"（责任编辑：薛诗汉） "},{"id":"65421124f5682e8b1277b774","title":"潘多梅星球的台风","author":"文／张冠仁","editor":"（责任编辑：薛诗汉） "},{"id":"65421126f5682e8b1277b776","title":"某年某日某首歌","author":"文／高晓松","editor":"（责任编辑：薛诗汉） "},{"id":"65421129f5682e8b1277b778","title":"能帮我把这袋垃圾带下楼扔了吗","author":"文／曹寇","editor":"（责任编辑：薛诗汉） "},{"id":"6542112bf5682e8b1277b77a","title":"那年夏天","author":"文／张玮玮","editor":"责任编辑：薛诗汉 onewenzhang@wufazhuce.com"},{"id":"6542112df5682e8b1277b77c","title":"风波","author":"文／叫兽易小星","editor":"（责任编辑：薛诗汉） "},{"id":"6542112ff5682e8b1277b77e","title":"碎片","author":"文／韩寒","editor":"（责任编辑：薛诗汉） "},{"id":"65421132f5682e8b1277b780","title":"我们不能以平庸来反抗平庸","author":"文／苏更生","editor":"责任编辑：金子棋 jinziqi@wufazhuce.com专栏《给爱德华·诺顿写信》，于每周三更新。"},{"id":"65421134f5682e8b1277b782","title":"谁在文革时期听披头士?","author":"文／枪总008","editor":"责任编辑：小影 zhuxiaoying@wufazhuce.com本文付费转载自X博士"},{"id":"65421136f5682e8b1277b784","title":"希望和绝望不会同时消失","author":"文／苏更生","editor":"责任编辑：金子棋 jinziqi@wufazhuce.com专栏《给爱德华·诺顿写信》，于每周三更新。"},{"id":"65421138f5682e8b1277b786","title":"真实故事 · 他的职业是病人","author":"文／ 龚菁琦","editor":"责任编辑：向可 xiangke@wufazhuce.com本文付费转载自人物。"},{"id":"6542113bf5682e8b1277b788","title":"再启程，别来惊慌","author":"文／花大钱","editor":"责任编辑：金子棋 jinziqi@wufazhuce.com"},{"id":"6542113df5682e8b1277b78a","title":"对不起，前方没有支撑物","author":"文／黄集伟","editor":"责任编辑：向可 xiangke@wufazhuce.com"},{"id":"6542113ff5682e8b1277b78c","title":"大雨中的楼群——城市人物塑像（1）","author":"文／淡豹","editor":"责任编辑：向可 xiangke@wufazhuce.com淡豹的《城市人物塑像》专栏于每周五在ONE独家首发。"},{"id":"65421141f5682e8b1277b78e","title":"你想要的样子","author":"文／仲尼","editor":"责任编辑：金子棋 jinziqi@wufazhuce.com"},{"id":"65421144f5682e8b1277b790","title":"说脏话的人比不说的人更加可靠","author":"文／黄集伟","editor":"责任编辑：向可 xiangke@wufazhuce.com"},{"id":"65421146f5682e8b1277b792","title":"你这么一直笑我们没办法做笔录","author":"文／黄集伟","editor":"责任编辑：向可 xiangke@wufazhuce.com"},{"id":"65421148f5682e8b1277b794","title":"能有一个自己的座位","author":"文／刘墨闻","editor":"责任编辑：金子棋 jinziqi@wufazhuce.com本文付费转载自刘墨闻。"},{"id":"6542114af5682e8b1277b796","title":"吃食和文学","author":"文／汪曾祺","editor":"责任编辑：向可 xiangke@wufazhuce.com本文选自汪曾祺《生活，是很好玩的》。"},{"id":"6542114cf5682e8b1277b798","title":"妈妈","author":"文／陈永和","editor":"责任编辑：金子棋 jinziqi@wufazhuce.com本文付费转载自《上海文学》。"},{"id":"6542114ff5682e8b1277b79a","title":"去崇明岛上看一看","author":"文／周嘉宁","editor":"责任编辑：金子棋 jinziqi@wufazhuce.com本文付费转载自《上海文学》。"},{"id":"65421151f5682e8b1277b79c","title":"不幸我是个女孩，更不幸是个演戏的","author":"文／袁雪芬","editor":"责任编辑：秦何人 qhr@wufazhuce.com"},{"id":"65421153f5682e8b1277b79e","title":"作业本：精神已经移民，留下肉体在此赚钱","author":"文／作业本","editor":"责任编辑：黄点点 tingting@wufazhuce.com"},{"id":"65421155f5682e8b1277b7a0","title":"文艺界泥石流汪曾祺","author":"文／乌潘潘","editor":"责任编辑：阿芙拉 afra@wufazhuce.com本文付费转载自微在Wezeit，有删减。"},{"id":"65421158f5682e8b1277b7a2","title":"世界上最坏的小猫","author":"文／苏更生","editor":"责任编辑：金子棋 jinziqi@wufazhuce.com本文付费转载自狐狸宅。"},{"id":"6542115af5682e8b1277b7a4","title":"东京，东京","author":"文／金一","editor":"责任编辑：向可 xiangke@wufazhuce.com本文经作者授权转载。"},{"id":"6542115cf5682e8b1277b7a6","title":"告诉你一棵稗子提心吊胆的春天","author":"文／黄集伟","editor":"责任编辑：向可 xiangke@wufazhuce.com"},{"id":"6542115ef5682e8b1277b7a8","title":"回家的意义","author":"文／姚瑶","editor":"责任编辑：金子棋 jinziqi@wufazhuce.com本文付费转载自姚瑶。"},{"id":"65421161f5682e8b1277b7aa","title":"一个青年网络作家的肖像","author":"文／远子","editor":"责任编辑：向可 xiangke@wufazhuce.com本文选自远子的《夜晚属于恋人》。"},{"id":"65421163f5682e8b1277b7ac","title":"好运与有勇气的人同在","author":"文／八月长安","editor":"责任编辑：金子棋 jinziqi@wufazhuce.com本文付费转载自八月长安。"},{"id":"65421165f5682e8b1277b7ae","title":"这一次，奥斯卡选择为“失败者”加冕","author":"文／吴呈杰","editor":"责任编辑：向可 xiangke@wufazhuce.com本文付费转载自人物。"},{"id":"65421167f5682e8b1277b7b0","title":"传奇古典谋杀的终结","author":"文／王天挺","editor":"责任编辑：林珊珊 033@wufazhuce.com"},{"id":"6542116af5682e8b1277b7b2","title":"六点半婆婆","author":"文／姚瑶","editor":"责任编辑：金子棋 jinziqi@wufazhuce.com本文付费转载自姚瑶。"},{"id":"6542116cf5682e8b1277b7b4","title":"编剧根本写不出这样的剧本","author":"文／李诞","editor":"责任编辑：向可 xiangke@wufazhuce.com"},{"id":"6542116ef5682e8b1277b7b6","title":"你马不停蹄的爱情，只是一段段故事梗概","author":"文／韩松落","editor":"责任编辑：金子棋 jinziqi@wufazhuce.com本文付费转载自韩松落见好。"},{"id":"65421170f5682e8b1277b7b8","title":"妈妈和月亮都只有一个","author":"文／花大钱","editor":"责任编辑：金子棋 jinziqi@wufazhuce.com"},{"id":"65421173f5682e8b1277b7ba","title":"北京小吃为什么难吃","author":"文／吴余","editor":"责任编辑：向可 xiangke@wufazhuce.com本文付费转载自大象公会。"},{"id":"65421175f5682e8b1277b7bc","title":"过房","author":"文／张怡微","editor":"责任编辑：金子棋 jinziqi@wufazhuce.com本文付费转载自《上海文学》。"},{"id":"65421177f5682e8b1277b7be","title":"我妈悄悄坐到我身边问“你什么时候给我钱”","author":"文／刘同","editor":"责任编辑：金子棋 jinziqi@wufazhuce.com本文付费转载自素色咦院。"},{"id":"65421179f5682e8b1277b7c0","title":"一周语文丨活得宛如一个高仿","author":"文／黄集伟","editor":"责任编辑：向可 xiangke@wufazhuce.com"},{"id":"6542117cf5682e8b1277b7c2","title":"在拉丁美洲开一家中国餐馆是什么样的体验？","author":"文／红旗手","editor":"责任编辑：阿芙拉 afra@wufazhuce.com本文付费转载自温柔且酷。"},{"id":"6542117ef5682e8b1277b7c4","title":"相比于古代上下班，你算赶上好时候啦","author":"文／拾壹路","editor":"责任编辑：阿芙拉 afra@wufazhuce.com本文付费转载自拾壹路。"},{"id":"65421180f5682e8b1277b7c6","title":"被老虎咬死的“罪人”活该么？","author":"文／冉云飞","editor":"责任编辑：阿芙拉 afra@wufazhuce.com本文付费转载自七个作家。"},{"id":"65421182f5682e8b1277b7c8","title":"博物馆之心","author":"文／糖匪","editor":"责任编辑：金子棋 jinziqi@wufazhuce.com"},{"id":"65421185f5682e8b1277b7ca","title":"老派","author":"文／沈芸","editor":"责任编辑：金子棋 jinziqi@wufazhuce.com本文付费转载自文汇笔会。"},{"id":"65421187f5682e8b1277b7cc","title":"七浦路男孩的快递江湖","author":"文／杨楠","editor":"责任编辑：阿芙拉 afra@wufazhuce.com本文付费转载自ELLEMEN睿士。"},{"id":"65421189f5682e8b1277b7ce","title":"关于春节的那些批评","author":"文／刘墨闻","editor":"责任编辑：金子棋 jinziqi@wufazhuce.com"},{"id":"6542118bf5682e8b1277b7d0","title":"我去买菜被点穴","author":"文／马东","editor":"责任编辑：金子棋 jinziqi@wufazhuce.com本文付费转载自桥下有人。"},{"id":"6542118df5682e8b1277b7d2","title":"你人生的句子那么长，我做逗号又何妨","author":"文／张晓晗","editor":"责任编辑：向可 xiangke@wufazhuce.com"},{"id":"65421190f5682e8b1277b7d4","title":"香港的铺子，好景常在","author":"文／葛亮","editor":"责任编辑：小影 zhuxiaoying@wufazhuce.com本文经作者本人授权转载"},{"id":"65421192f5682e8b1277b7d6","title":"我要为你背作文","author":"文／阿缺","editor":"责任编辑：金子棋 jinziqi@wufazhuce.com"},{"id":"65421194f5682e8b1277b7d8","title":"日本流浪汉生存指南","author":"文／李淼","editor":"责任编辑：阿芙拉 afra@wufazhuce.com本文付费转载自李淼。"},{"id":"65421196f5682e8b1277b7da","title":"一截一截的人生","author":"文／蒋方舟","editor":"责任编辑：阿芙拉 afra@wufazhuce.com本文付费转载自七个作家。"},{"id":"65421199f5682e8b1277b7dc","title":"那些绝望的香港年轻人","author":"文／ 吴应时","editor":"责任编辑：向可 xiangke@wufazhuce.com本文经作者授权转载。"},{"id":"6542119bf5682e8b1277b7de","title":"午夜起来听寂静","author":"文／周云蓬","editor":"责任编辑：金子棋 jinziqi@wufazhuce.com"},{"id":"6542119df5682e8b1277b7e0","title":"没有手机的时代，人们如何排解空虚","author":"文／马东","editor":"责任编辑：金子棋 jinziqi@wufazhuce.com本文付费转载自桥下有人。"},{"id":"6542119ff5682e8b1277b7e2","title":"与白百何有关的日子","author":"文／马东","editor":"责任编辑：金子棋 jinziqi@wufazhuce.com本文付费转载自桥下有人。"},{"id":"654211a2f5682e8b1277b7e4","title":"疯狂的果实","author":"文／潘妤","editor":"责任编辑：阿芙拉 afra@wufazhuce.com本文付费转载自ELLEMEN睿士。"},{"id":"654211a4f5682e8b1277b7e6","title":"一家人，最要紧的是整整齐齐地受罪","author":"文／Milo","editor":"责任编辑：阿芙拉 afra@wufazhuce.com本文付费转载自简单心理。"},{"id":"654211a6f5682e8b1277b7e8","title":"正月剃头死舅舅？谁说的！","author":"文／拾壹路","editor":"责任编辑：阿芙拉 afra@wufazhuce.com本文付费转载自拾壹路。"},{"id":"654211a8f5682e8b1277b7ea","title":"性、BP机和录像带","author":"文／马东","editor":"责任编辑：金子棋 jinziqi@wufazhuce.com本文付费转载自桥下有人。"},{"id":"654211aef5682e8b1277b7ec","title":"我翻开外公的家书，才发现他没和我说过的故事","author":"文／倪玮","editor":"责任编辑：阿芙拉 afra@wufazhuce.com本文付费转载自中国三明治。"},{"id":"654211b1f5682e8b1277b7ee","title":"远行的人，你是否也回到了家","author":"文／花大钱","editor":"责任编辑：金子棋 jinziqi@wufazhuce.com"},{"id":"654211b3f5682e8b1277b7f0","title":"保持着一种互相嫌弃又互不打扰的默契","author":"文／黄集伟","editor":"责任编辑：向可 xiangke@wufazhuce.com"},{"id":"654211b5f5682e8b1277b7f2","title":"看完林徽因过的这个春节，你还好意思讽刺她吗？","author":"文／李舒","editor":"责任编辑：阿芙拉 afra@wufazhuce.com本文付费转载自山河小岁月。"},{"id":"654211b7f5682e8b1277b7f4","title":"超人弟弟","author":"文／金一","editor":"责任编辑：向可 xiangke@wufazhuce.com"},{"id":"654211baf5682e8b1277b7f6","title":"少交朋友，多看月亮","author":"文／黄集伟","editor":"责任编辑：向可 xiangke@wufazhuce.com"},{"id":"654211bcf5682e8b1277b7f8","title":"幸好你没参加过这八个心理学实验","author":"文／何为","editor":"责任编辑：向可 xiangke@wufazhuce.com本文付费转载自友心人。"},{"id":"654211bef5682e8b1277b7fa","title":"男子不宅便是德","author":"文／黄集伟","editor":"责任编辑：向可 xiangke@wufazhuce.com"},{"id":"654211c0f5682e8b1277b7fc","title":"愚人节是个好开始","author":"文／SH","editor":"责任编辑：77 jinziqi@wufazhuce.com史航专栏《本文献给少女棋子》第一期"},{"id":"654211c3f5682e8b1277b7fe","title":"当编剧聊影视时，他们在聊什么","author":"文／宋方金","editor":"责任编辑：黄点点 tingting@wufazhuce.com"},{"id":"654211c5f5682e8b1277b800","title":"那个不是很厉害的人","author":"文／苏晟","editor":"责任编辑：向可 xiangke@wufazhuce.com"},{"id":"654211c7f5682e8b1277b802","title":"与王朔和徐静蕾有关的日子","author":"文／马东","editor":"责任编辑：金子棋 jinziqi@wufazhuce.com本文付费转载自桥下有人。"},{"id":"654211c9f5682e8b1277b804","title":"要从北上广看西宁而不是从西宁看北上广","author":"文／黄集伟","editor":"责任编辑：向可 xiangke@wufazhuce.com"},{"id":"654211ccf5682e8b1277b806","title":"残忍","author":"文／ 贾行家","editor":"责任编辑：向可 xiangke@wufazhuce.com本文有部分删减。"},{"id":"654211cef5682e8b1277b808","title":"新年的吃","author":"文／沈书枝","editor":"责任编辑：阿芙拉 afra@wufazhuce.com本文经作者授权转载。"},{"id":"654211d0f5682e8b1277b80a","title":"我在皇后镇，闯进了“活人”社区","author":"文／姚瑶","editor":"责任编辑：金子棋 jinziqi@wufazhuce.com本文付费转载自姚瑶。"},{"id":"654211d2f5682e8b1277b80c","title":"我们的客栈","author":"文／刘墨闻","editor":"责任编辑：金子棋 jinziqi@wufazhuce.com"},{"id":"654211d5f5682e8b1277b80e","title":"“不记得我啦？小时候我还抱过你呐！”","author":"文／Milo","editor":"责任编辑：阿芙拉 afra@wufazhuce.com本文付费转载自简单心理。"},{"id":"654211d7f5682e8b1277b810","title":"四位形婚者，一场仓皇表演","author":"文／李刚、徐佳","editor":"责任编辑：阿芙拉 afra@wufazhuce.com本文付费转载自ELLEMEN睿士。"},{"id":"654211d9f5682e8b1277b812","title":"为啥俄罗斯人从来不笑？！","author":"文／文谈","editor":"责任编辑：阿芙拉 afra@wufazhuce.com本文付费转载自文谈。"},{"id":"654211dbf5682e8b1277b814","title":"总之，我就这样谈起了南美洲恋爱","author":"文／红旗手","editor":"责任编辑：阿芙拉 afra@wufazhuce.com本文付费转载自温柔且酷。"},{"id":"654211def5682e8b1277b816","title":"回家很累？真正的成年人需要与父母“分手”","author":"文／ KnowYourself","editor":"责任编辑：金子棋 jinziqi@wufazhuce.com本文付费转载自KnowYourself。"},{"id":"654211e0f5682e8b1277b818","title":"“父爱”这种怪东西","author":"文／姚瑶","editor":"责任编辑：金子棋 jinziqi@wufazhuce.com本文付费转载自姚瑶。"},{"id":"654211e2f5682e8b1277b81a","title":"他离开以后","author":"文／刘墨闻","editor":"责任编辑：金子棋 jinziqi@wufazhuce.com"},{"id":"654211e4f5682e8b1277b81c","title":"为最著名的裸男月历贡献肉体，是怎样一种体验？","author":"文／唐卓人","editor":"责任编辑：阿芙拉 afra@wufazhuce.com本文付费转载自ELLEMEN睿士。"},{"id":"654211e7f5682e8b1277b81e","title":"等待","author":"文／大头马","editor":"责任编辑：金子棋 jinziqi@wufazhuce.com本文付费转载自雅致的精神病院。"},{"id":"654211e9f5682e8b1277b820","title":"讨厌的书籍腰封极简史 ","author":"文／史壳郎","editor":"责任编辑：阿芙拉 afra@wufazhuce.com本文付费转载自极简史。"},{"id":"654211ebf5682e8b1277b822","title":"古人对孩子的七大奇葩看法","author":"文／文谈","editor":"责任编辑：阿芙拉 afra@wufazhuce.com本文付费转载自文谈。"},{"id":"654211edf5682e8b1277b824","title":"分身国","author":"文／沈大成","editor":"责任编辑：金子棋 jinziqi@wufazhuce.com"}]